LICENSE.md
MANIFEST.in
README.md
setup.py
django_dyn_dt/__init__.py
django_dyn_dt/admin.py
django_dyn_dt/apps.py
django_dyn_dt/helpers.py
django_dyn_dt/models.py
django_dyn_dt/tests.py
django_dyn_dt/urls.py
django_dyn_dt/views.py
django_dyn_dt/templates/404.html
django_dyn_dt/templates/index.html
django_dyn_dt/templates/static/data/index.js
django_dyn_dt/templates/static/src/index.js
django_dyn_dt/templates/static/src/controller/index.js
django_dyn_dt/templates/static/src/events/index.js
django_dyn_dt/templates/static/src/form/index.js
django_dyn_dt/templates/static/src/images/csv.svg
django_dyn_dt/templates/static/src/images/excel.svg
django_dyn_dt/templates/static/src/images/pdf.svg
django_dyn_dt/templates/static/src/style/myStyle.css
django_dynamic_datatb.egg-info/PKG-INFO
django_dynamic_datatb.egg-info/SOURCES.txt
django_dynamic_datatb.egg-info/dependency_links.txt
django_dynamic_datatb.egg-info/not-zip-safe
django_dynamic_datatb.egg-info/requires.txt
django_dynamic_datatb.egg-info/top_level.txt
docs/blank.txt